[
  {
    "student_id": "u_stu_01",
    "topic_id": "t-chem-reactions",
    "attempts": 4,
    "correct": 4,
    "last_attempt": "2025-09-20T16:00:00"
  },
  {
    "student_id": "u_stu_01",
    "topic_id": "t-chem-ph",
    "attempts": 8,
    "correct": 3,
    "last_attempt": "2025-09-20T16:00:00"
  },
  {
    "student_id": "u_stu_01",
    "topic_id": "t-chem-metals",
    "attempts": 5,
    "correct": 4,
    "last_attempt": "2025-09-20T16:00:00"
  },
  {
    "student_id": "u_stu_02",
    "topic_id": "t-chem-reactions",
    "attempts": 8,
    "correct": 3,
    "last_attempt": "2025-09-20T16:00:00"
  },
  {
    "student_id": "u_stu_02",
    "topic_id": "t-chem-ph",
    "attempts": 8,
    "correct": 3,
    "last_attempt": "2025-09-20T16:00:00"
  },
  {
    "student_id": "u_stu_02",
    "topic_id": "t-chem-metals",
    "attempts": 4,
    "correct": 3,
    "last_attempt": "2025-09-20T16:00:00"
  },
  {
    "student_id": "u_stu_03",
    "topic_id": "t-chem-reactions",
    "attempts": 4,
    "correct": 2,
    "last_attempt": "2025-09-20T16:00:00"
  },
  {
    "student_id": "u_stu_03",
    "topic_id": "t-chem-ph",
    "attempts": 8,
    "correct": 5,
    "last_attempt": "2025-09-20T16:00:00"
  },
  {
    "student_id": "u_stu_03",
    "topic_id": "t-chem-metals",
    "attempts": 8,
    "correct": 3,
    "last_attempt": "2025-09-20T16:00:00"
  },
  {
    "student_id": "u_stu_04",
    "topic_id": "t-chem-reactions",
    "attempts": 4,
    "correct": 3,
    "last_attempt": "2025-09-20T16:00:00"
  },
  {
    "student_id": "u_stu_04",
    "topic_id": "t-chem-ph",
    "attempts": 3,
    "correct": 3,
    "last_attempt": "2025-09-20T16:00:00"
  },
  {
    "student_id": "u_stu_04",
    "topic_id": "t-chem-metals",
    "attempts": 7,
    "correct": 3,
    "last_attempt": "2025-09-20T16:00:00"
  },
  {
    "student_id": "u_stu_05",
    "topic_id": "t-chem-reactions",
    "attempts": 3,
    "correct": 3,
    "last_attempt": "2025-09-20T16:00:00"
  },
  {
    "student_id": "u_stu_05",
    "topic_id": "t-chem-ph",
    "attempts": 3,
    "correct": 2,
    "last_attempt": "2025-09-20T16:00:00"
  },
  {
    "student_id": "u_stu_05",
    "topic_id": "t-chem-metals",
    "attempts": 8,
    "correct": 7,
    "last_attempt": "2025-09-20T16:00:00"
  }
]